mend_sbom_export_cli/__init__.py
mend_sbom_export_cli/_version.py
mend_sbom_export_cli/conftest.py
mend_sbom_export_cli/const.py
mend_sbom_export_cli/sbom_export_cli.py
mend_sbom_export_cli-23.12.1.dist-info/LICENSE
mend_sbom_export_cli-23.12.1.dist-info/METADATA
mend_sbom_export_cli-23.12.1.dist-info/WHEEL
mend_sbom_export_cli-23.12.1.dist-info/entry_points.txt
mend_sbom_export_cli-23.12.1.dist-info/top_level.txt
mend_sbom_export_cli-23.12.1.dist-info/RECORD
