Metadata-Version: 2.1
Name: mend-sbom-export-cli
Version: 23.12.1
Summary: A utility to create SBOM Reports in the SPDX or CDX formats
Home-page: https://github.com/mend-toolkit/sbom-export-cli
Author: Mend Professional Services
Author-email: ps@mend.io
License: LICENSE.txt
Platform: UNKNOWN
Classifier: Programming Language :: Python :: 3.9
Classifier: Programming Language :: Python :: 3.10
Classifier: Programming Language :: Python :: 3.11
Classifier: License :: OSI Approved :: Apache Software License
Classifier: Operating System :: OS Independent
Requires-Python: >=3.9
License-File: LICENSE
Requires-Dist: configparser ~=6.0.0
Requires-Dist: requests ~=2.31.0
